openinference/semconv/__init__.py
openinference/semconv/py.typed
openinference/semconv/version.py
openinference/semconv/resource/__init__.py
openinference/semconv/trace/__init__.py
openinference_semantic_conventions-0.1.23.dist-info/METADATA
openinference_semantic_conventions-0.1.23.dist-info/WHEEL
openinference_semantic_conventions-0.1.23.dist-info/licenses/LICENSE
openinference_semantic_conventions-0.1.23.dist-info/RECORD
